adblock-0.6.0.dist-info/METADATA
adblock-0.6.0.dist-info/WHEEL
adblock/__init__.py
adblock/adblock.pyi
adblock/py.typed
adblock/adblock.abi3.so
adblock-0.6.0.dist-info/RECORD
