Metadata-Version: 2.1
Name: adblock
Version: 0.6.0
Classifier: Programming Language :: Python
Classifier: Programming Language :: Rust
Classifier: License :: OSI Approved :: MIT License
Classifier: License :: OSI Approved :: Apache Software License
Home-Page: https://github.com/ArniDagur/python-adblock
Author: Árni Dagur <arni@dagur.eu>
Author-email: Árni Dagur <arni@dagur.eu>
License: MIT OR Apache-2.0
Requires-Python: >=3.7
Project-URL: Source Code, https://github.com/ArniDagur/python-adblock
